callpy/__init__.py
callpy/app.py
callpy/concurrency.py
callpy/manager.py
callpy/resp.py
callpy/server.py
callpy/supervisor.py
callpy/watcher.py
callpy/web/__init__.py
callpy/web/blueprints.py
callpy/web/datastructures.py
callpy/web/errors.py
callpy/web/formparsers.py
callpy/web/handlers.py
callpy/web/protocol.py
callpy/web/request.py
callpy/web/response.py
callpy/web/routing.py
callpy/web/types.py
callpy/web/utils.py
callpy-0.4.0.dist-info/LICENSE
callpy-0.4.0.dist-info/METADATA
callpy-0.4.0.dist-info/WHEEL
callpy-0.4.0.dist-info/entry_points.txt
callpy-0.4.0.dist-info/top_level.txt
callpy-0.4.0.dist-info/RECORD
