Metadata-Version: 2.1
Name: callpy
Version: 0.4.0
Summary: multi protocol, auto-cluster server framework.
Home-page: https://github.com/pyflow/callpy
Author: Wei Zhuo
Author-email: zeaphoo@qq.com
License: MIT
Classifier: Development Status :: 4 - Beta
Classifier: Environment :: Web Environment
Classifier: Intended Audience :: Developers
Classifier: License :: OSI Approved :: BSD License
Classifier: Operating System :: OS Independent
Classifier: Topic :: Internet :: WWW/HTTP
Classifier: Programming Language :: Python :: 3
Classifier: Programming Language :: Python :: 3.6
Classifier: Programming Language :: Python :: 3.7
Classifier: Programming Language :: Python :: 3.8
Classifier: Programming Language :: Python :: 3.9
Classifier: Programming Language :: Python :: 3.10
Classifier: Programming Language :: Python :: Implementation :: CPython
License-File: LICENSE
Requires-Dist: websockets >=9.0
Requires-Dist: httptools >=0.4.0
Requires-Dist: basepy >=0.3.1
Requires-Dist: aiofiles
Requires-Dist: setproctitle
